{".class": "MypyFile", "_fullname": "preconvert.register", "is_partial_stub_package": false, "is_stub": false, "names": {".class": "SymbolTable", "Any": {".class": "SymbolTableNode", "cross_ref": "typing.Any", "kind": "Gdef"}, "Callable": {".class": "SymbolTableNode", "cross_ref": "typing.Callable", "kind": "Gdef"}, "Dict": {".class": "SymbolTableNode", "cross_ref": "typing.Dict", "kind": "Gdef"}, "ExistingConverter": {".class": "SymbolTableNode", "cross_ref": "preconvert.exceptions.ExistingConverter", "kind": "Gdef"}, "Text": {".class": "SymbolTableNode", "cross_ref": "typing.Text", "kind": "Gdef"}, "__doc__": {".class": "SymbolTableNode", "kind": "Gdef", "node": {".class": "Var", "flags": ["is_ready"], "fullname": "preconvert.register.__doc__", "name": "__doc__", "type": "builtins.str"}}, "__file__": {".class": "SymbolTableNode", "kind": "Gdef", "node": {".class": "Var", "flags": ["is_ready"], "fullname": "preconvert.register.__file__", "name": "__file__", "type": "builtins.str"}}, "__name__": {".class": "SymbolTableNode", "kind": "Gdef", "node": {".class": "Var", "flags": ["is_ready"], "fullname": "preconvert.register.__name__", "name": "__name__", "type": "builtins.str"}}, "__package__": {".class": "SymbolTableNode", "kind": "Gdef", "node": {".class": "Var", "flags": ["is_ready"], "fullname": "preconvert.register.__package__", "name": "__package__", "type": "builtins.str"}}, "bson": {".class": "SymbolTableNode", "kind": "Gdef", "node": {".class": "Var", "flags": [], "fullname": "preconvert.register.bson", "name": "bson", "type": {".class": "Instance", "args": [{".class": "CallableType", "arg_kinds": [2, 4], "arg_names": [null, null], "arg_types": [{".class": "AnyType", "missing_import_name": null, "source_any": null, "type_of_any": 4}, {".class": "AnyType", "missing_import_name": null, "source_any": null, "type_of_any": 4}], "bound_args": [], "def_extras": {}, "fallback": "builtins.function", "implicit": false, "is_ellipsis_args": true, "name": null, "ret_type": {".class": "AnyType", "missing_import_name": null, "source_any": null, "type_of_any": 4}, "variables": []}], "type_ref": "functools.partial"}}}, "converter": {".class": "SymbolTableNode", "kind": "Gdef", "node": {".class": "FuncDef", "arg_kinds": [2, 5, 5, 5], "arg_names": ["kinds", "scope", "store", "override"], "flags": [], "fullname": "preconvert.register.converter", "name": "converter", "type": {".class": "CallableType", "arg_kinds": [2, 5, 5, 5], "arg_names": ["kinds", "scope", "store", "override"], "arg_types": [{".class": "AnyType", "missing_import_name": null, "source_any": null, "type_of_any": 2}, "builtins.str", {".class": "Instance", "args": ["builtins.str", {".class": "Instance", "args": ["builtins.str", {".class": "CallableType", "arg_kinds": [2, 4], "arg_names": [null, null], "arg_types": [{".class": "AnyType", "missing_import_name": null, "source_any": null, "type_of_any": 4}, {".class": "AnyType", "missing_import_name": null, "source_any": null, "type_of_any": 4}], "bound_args": [], "def_extras": {}, "fallback": "builtins.function", "implicit": false, "is_ellipsis_args": true, "name": null, "ret_type": {".class": "AnyType", "missing_import_name": null, "source_any": null, "type_of_any": 4}, "variables": []}], "type_ref": "builtins.dict"}], "type_ref": "builtins.dict"}, "builtins.bool"], "bound_args": [], "def_extras": {"first_arg": null}, "fallback": "builtins.function", "implicit": false, "is_ellipsis_args": false, "name": "converter", "ret_type": {".class": "CallableType", "arg_kinds": [2, 4], "arg_names": [null, null], "arg_types": [{".class": "AnyType", "missing_import_name": null, "source_any": null, "type_of_any": 4}, {".class": "AnyType", "missing_import_name": null, "source_any": null, "type_of_any": 4}], "bound_args": [], "def_extras": {}, "fallback": "builtins.function", "implicit": false, "is_ellipsis_args": true, "name": null, "ret_type": {".class": "AnyType", "missing_import_name": null, "source_any": null, "type_of_any": 4}, "variables": []}, "variables": []}}}, "converters": {".class": "SymbolTableNode", "kind": "Gdef", "node": {".class": "Var", "flags": ["is_ready"], "fullname": "preconvert.register.converters", "name": "converters", "type": {".class": "Instance", "args": ["builtins.str", {".class": "Instance", "args": ["builtins.str", {".class": "CallableType", "arg_kinds": [2, 4], "arg_names": [null, null], "arg_types": [{".class": "AnyType", "missing_import_name": null, "source_any": null, "type_of_any": 4}, {".class": "AnyType", "missing_import_name": null, "source_any": null, "type_of_any": 4}], "bound_args": [], "def_extras": {}, "fallback": "builtins.function", "implicit": false, "is_ellipsis_args": true, "name": null, "ret_type": {".class": "AnyType", "missing_import_name": null, "source_any": null, "type_of_any": 4}, "variables": []}], "type_ref": "builtins.dict"}], "type_ref": "builtins.dict"}}}, "json": {".class": "SymbolTableNode", "kind": "Gdef", "node": {".class": "Var", "flags": [], "fullname": "preconvert.register.json", "name": "json", "type": {".class": "Instance", "args": [{".class": "CallableType", "arg_kinds": [2, 4], "arg_names": [null, null], "arg_types": [{".class": "AnyType", "missing_import_name": null, "source_any": null, "type_of_any": 4}, {".class": "AnyType", "missing_import_name": null, "source_any": null, "type_of_any": 4}], "bound_args": [], "def_extras": {}, "fallback": "builtins.function", "implicit": false, "is_ellipsis_args": true, "name": null, "ret_type": {".class": "AnyType", "missing_import_name": null, "source_any": null, "type_of_any": 4}, "variables": []}], "type_ref": "functools.partial"}}}, "msgpack": {".class": "SymbolTableNode", "kind": "Gdef", "node": {".class": "Var", "flags": [], "fullname": "preconvert.register.msgpack", "name": "msgpack", "type": {".class": "Instance", "args": [{".class": "CallableType", "arg_kinds": [2, 4], "arg_names": [null, null], "arg_types": [{".class": "AnyType", "missing_import_name": null, "source_any": null, "type_of_any": 4}, {".class": "AnyType", "missing_import_name": null, "source_any": null, "type_of_any": 4}], "bound_args": [], "def_extras": {}, "fallback": "builtins.function", "implicit": false, "is_ellipsis_args": true, "name": null, "ret_type": {".class": "AnyType", "missing_import_name": null, "source_any": null, "type_of_any": 4}, "variables": []}], "type_ref": "functools.partial"}}}, "partial": {".class": "SymbolTableNode", "cross_ref": "functools.partial", "kind": "Gdef"}}, "path": "preconvert/register.py"}